gd-0.1.11.dist-info/dependency_links.txt
gd-0.1.11.dist-info/entry_points.txt
gd-0.1.11.dist-info/METADATA
gd-0.1.11.dist-info/top_level.txt
gd-0.1.11.dist-info/WHEEL
gd/__init__.py
gd-0.1.11.dist-info/RECORD