Metadata-Version: 2.1
Name: gd
Version: 0.1.11
Summary: Python GoodData SDK library
Project-URL: Homepage, https://bizztreat.com
Author: Tomas Votava
Author-email: tomas.votava@bizztreat.com
Classifier: Programming Language :: Python :: 3
Classifier: License :: OSI Approved :: MIT License
Classifier: Operating System :: OS Independent
Requires-Dist: certifi==2020.6.20
Requires-Dist: chardet==3.0.4
Requires-Dist: idna==2.10
Requires-Dist: mako==1.1.3
Requires-Dist: markdown==3.2.2
Requires-Dist: markupsafe==1.1.1
Requires-Dist: pdoc3==0.9.1
Requires-Dist: requests==2.24.0
Requires-Dist: urllib3==1.25.10
